logging_opentelemetry_format/__init__.py
logging_opentelemetry_format/utils.py
tests/__init__.py
tests/conftest.py
tests/test_logging.py
logging_opentelemetry_format-0.0.1.dist-info/LICENSE
logging_opentelemetry_format-0.0.1.dist-info/METADATA
logging_opentelemetry_format-0.0.1.dist-info/WHEEL
logging_opentelemetry_format-0.0.1.dist-info/top_level.txt
logging_opentelemetry_format-0.0.1.dist-info/RECORD
