Metadata-Version: 2.1
Name: logging-opentelemetry-format
Version: 0.0.1
Summary: opentelemetry formatter for python logging module.
Home-page: https://github.com/jha-hitesh/logging-opentelemetry-format
Author: hitesh jha
Author-email: hitesh4official@gmail.com
Classifier: Programming Language :: Python :: 3
Classifier: Operating System :: OS Independent
Requires-Python: >=3.6
License-File: LICENSE
Requires-Dist: ujson
Requires-Dist: opentelemetry-api (==1.14.0)
Requires-Dist: opentelemetry-sdk (==1.14.0)
